{"api-examples.md":"KiwwbM7t","community_blog_index.md":"Bbvk2NKP","community_experience_first-time.md":"CWMYSRrx","community_experience_save-money.md":"CtiP1-ay","community_experience_solo-safety.md":"BVUZk6HO","community_faq.md":"pvt7MjH6","community_forum.md":"Cujgz0Gj","community_index.md":"CpPNjwIe","community_partner.md":"CO6PE_E5","community_partner_europe-2024.md":"C-pn2ZUz","community_partner_europe.md":"DpHsY9BQ","community_partner_rtw-partner.md":"CkwjyMT8","community_partner_sea-backpack.md":"D-0Dqoq0","community_partner_sea.md":"Bq50JE89","guide_accommodation.md":"DKkSJMTo","guide_budget.md":"qJ5_uIM7","guide_getting-started.md":"Cz39Zgk3","guide_preparation.md":"DHOUInUg","guide_route.md":"OjIL9dwp","guide_time.md":"XwskPIPS","guide_transport.md":"DXGHJlri","guide_visa.md":"BizYVGmX","index.md":"B_bKByvw","markdown-examples.md":"Bbnf_R2F","readme.md":"B-XgkqVO","social_bilibili.md":"DbCKirmt","social_wechat.md":"Bb-clvM2","social_xiaohongshu.md":"CJtoKVzg","special_destinations_africa.md":"CbPEGQRq","special_destinations_americas.md":"BWhtbrkn","special_destinations_asia.md":"BfFs8PMK","special_destinations_europe.md":"BQ2tzAIa","special_destinations_index.md":"yCFAElWF","special_destinations_oceania.md":"CCwiCgqt","special_experience.md":"BWH5bGIN","special_food.md":"8WpOEakz","special_index.md":"CbkS-o3N","special_photography.md":"6ygGVBc8","tools_budget-calculator.md":"Bn54CcDE","tools_index.md":"Bvdnr6RL","tools_itinerary-planner.md":"u-LhCXwP","tools_route-optimizer.md":"BXsEyVea","tools_visa-tracker.md":"CVSNmA27"}
